parametrization_cookbook/__init__.py
parametrization_cookbook/_common.py
parametrization_cookbook/_common_base.py
parametrization_cookbook/_common_matrices.py
parametrization_cookbook/_common_scalars.py
parametrization_cookbook/_common_tuples.py
parametrization_cookbook/_common_vectors.py
parametrization_cookbook/jax.py
parametrization_cookbook/numpy.py
parametrization_cookbook/torch.py
parametrization_cookbook/functions/__init__.py
parametrization_cookbook/functions/_doc_tools.py
parametrization_cookbook/functions/_dummy.py
parametrization_cookbook/functions/jax.py
parametrization_cookbook/functions/numpy.py
parametrization_cookbook/functions/torch.py
parametrization_cookbook-0.18.dist-info/LICENSE.md
parametrization_cookbook-0.18.dist-info/METADATA
parametrization_cookbook-0.18.dist-info/WHEEL
parametrization_cookbook-0.18.dist-info/top_level.txt
parametrization_cookbook-0.18.dist-info/RECORD
