Metadata-Version: 2.1
Name: parametrization-cookbook
Version: 0.18
Summary: Implementation and helpers of the Parametrization Cookbook
Home-page: UNKNOWN
Author: Jean-Benoist Leger
Author-email: jbleger@hds.utc.fr
License: MIT
Project-URL: Source, https://gitlab.com/jbleger/parametrization-cookbook
Project-URL: Documentation, https://jbleger.gitlab.io/parametrization-cookbook/index.html
Platform: UNKNOWN
Classifier: Development Status :: 3 - Alpha
Classifier: Intended Audience :: Science/Research
Classifier: License :: OSI Approved :: MIT License
Classifier: Programming Language :: Python :: 3 :: Only
Requires-Python: >=3
License-File: LICENSE.md
Requires-Dist: numpy
Requires-Dist: scipy
